{
  "title": "2024\u201325_Big_Bash_League_season",
  "url": "https://en.wikipedia.org/wiki/2024\u201325_Big_Bash_League_season",
  "summary": "The 2024\u201325 Big Bash League season or BBL|14 is the fourteenth season of the Big Bash League (BBL), the professional men's Twenty20 domestic cricket competition in Australia. The tournament is being played from 15 December 2024, with the final scheduled to be held on 27 January 2025. Brisbane Heat were the defending champions but failed to qualify from the league stage.",
  "content": [
    {
      "section_title": "Background",
      "section_content": [
        {
          "sentence": "On 10 July 2024, it was announced that Big Bash League would return for a fourteenth season in 2024, being held from 15 December 2024, with the final scheduled to be held on 27 January 2025",
          "refs": []
        },
        {
          "sentence": "The 2025 season will clash with the Super Smash, Bangladesh Premier League, SA20 and International League T20",
          "refs": []
        },
        {
          "sentence": "On 1 September 2024, the players draft was held to determine the lineups of the eight clubs for the 2024 season.",
          "refs": []
        }
      ],
      "subsections": []
    },
    {
      "section_title": "Draft",
      "section_content": [
        {
          "sentence": "The 2024\u201325 season players draft was held on 1 September 2024",
          "refs": []
        }
      ],
      "subsections": []
    },
    {
      "section_title": "Squads",
      "section_content": [],
      "subsections": []
    },
    {
      "section_title": "Venues",
      "section_content": [],
      "subsections": []
    },
    {
      "section_title": "Standings",
      "section_content": [],
      "subsections": [
        {
          "section_title": "Points table",
          "section_content": [],
          "subsections": []
        },
        {
          "section_title": "Win\u2013loss table",
          "section_content": [
            {
              "sentence": "Below is a summary of results for each team's ten regular season matches, plus finals where applicable, in chronological order",
              "refs": []
            },
            {
              "sentence": "A team's opponent for any given match is listed above the margin of victory/defeat.",
              "refs": []
            }
          ],
          "subsections": []
        },
        {
          "section_title": "Match summary",
          "section_content": [],
          "subsections": []
        }
      ]
    },
    {
      "section_title": "League stage",
      "section_content": [
        {
          "sentence": "On 12 July 2024, Cricket Australia confirmed the full schedule for the tournament",
          "refs": []
        }
      ],
      "subsections": []
    },
    {
      "section_title": "Finals",
      "section_content": [],
      "subsections": [
        {
          "section_title": "Qualifier",
          "section_content": [],
          "subsections": []
        },
        {
          "section_title": "Knockout",
          "section_content": [],
          "subsections": []
        },
        {
          "section_title": "Challenger",
          "section_content": [],
          "subsections": []
        },
        {
          "section_title": "Final",
          "section_content": [],
          "subsections": []
        }
      ]
    },
    {
      "section_title": "Team of the Tournament",
      "section_content": [
        {
          "sentence": "The Big Bash announced it's BBL 14 Team of the Tournament on Thursday January 23",
          "refs": []
        },
        {
          "sentence": "It features the best playing eleven across the tournament as well as a twelfth man",
          "refs": []
        },
        {
          "sentence": "The Brisbane Heat is the only team not to feature a player.",
          "refs": []
        },
        {
          "sentence": "Note: Statistics only include regular season games (excludes finals)",
          "refs": []
        }
      ],
      "subsections": []
    },
    {
      "section_title": "Season statistics",
      "section_content": [],
      "subsections": [
        {
          "section_title": "Team Records",
          "section_content": [],
          "subsections": [
            {
              "section_title": "Highest Totals",
              "section_content": [],
              "subsections": []
            },
            {
              "section_title": "Lowest Totals",
              "section_content": [],
              "subsections": []
            }
          ]
        },
        {
          "section_title": "Batting Records",
          "section_content": [],
          "subsections": [
            {
              "section_title": "Most runs",
              "section_content": [],
              "subsections": []
            },
            {
              "section_title": "Highest Scores",
              "section_content": [],
              "subsections": []
            },
            {
              "section_title": "Highest Strike Rate",
              "section_content": [],
              "subsections": []
            },
            {
              "section_title": "Highest Batting Average",
              "section_content": [],
              "subsections": []
            },
            {
              "section_title": "Most Sixes",
              "section_content": [],
              "subsections": []
            },
            {
              "section_title": "Most Fours",
              "section_content": [],
              "subsections": []
            }
          ]
        },
        {
          "section_title": "Bowling Records",
          "section_content": [],
          "subsections": [
            {
              "section_title": "Most Wickets",
              "section_content": [],
              "subsections": []
            },
            {
              "section_title": "Best Economy Rates",
              "section_content": [],
              "subsections": []
            }
          ]
        }
      ]
    },
    {
      "section_title": "Attendance",
      "section_content": [
        {
          "sentence": "As of 22 January 2025 - Knockout (Sydney Thunder vs Melbourne Stars)",
          "refs": []
        }
      ],
      "subsections": [
        {
          "section_title": "Home Team Attendances",
          "section_content": [
            {
              "sentence": "As of 22 January 2025 - Knockout (Sydney Thunder vs Melbourne Stars)",
              "refs": []
            },
            {
              "sentence": "* Match played at secondary home",
              "refs": []
            }
          ],
          "subsections": []
        }
      ]
    },
    {
      "section_title": "See also",
      "section_content": [],
      "subsections": []
    },
    {
      "section_title": "Notes",
      "section_content": [],
      "subsections": []
    },
    {
      "section_title": "References",
      "section_content": [],
      "subsections": []
    },
    {
      "section_title": "External links",
      "section_content": [],
      "subsections": []
    }
  ],
  "references": {
    "13": "[ERROR retrieving ref link]",
    "14": "[ERROR retrieving ref link]",
    "15": "[ERROR retrieving ref link]",
    "16": "[ERROR retrieving ref link]",
    "66": "[ERROR retrieving ref link]",
    "1": "https://www.espncricinfo.com/story/bbl-fixtures-schedule-2024-25-bbl-window-for-australia-test-players-after-india-series-1442936",
    "2": "https://www.cricket.com.au/news/4055798/bbl14-mens-big-bash-league-season-schedule-fixtures-2024-25-summer-broadcast-details",
    "3": "https://www.espncricinfo.com/series/big-bash-league-2023-24-1386092/sydney-sixers-vs-brisbane-heat-final-1386137/match-report",
    "4": "https://www.foxsports.com.au/cricket/domestic-cricket/big-bash/cricket-australia-reveals-fixtures-for-202425-big-bash-league/news-story/0c662e663e9acc7f38cca18d6d63eb3f",
    "5": "https://www.espncricinfo.com/story/ilt20-to-clash-with-big-bash-league-sa20-and-bangladesh-premier-league-1462148",
    "6": "https://www.espncricinfo.com/story/melbourne-stars-get-first-pick-in-bbl-overseas-draft-14384410",
    "7": "https://www.instagram.com/p/C9_MZSryGxa/",
    "8": "https://www.espncricinfo.com/story/full-nominations-lists-for-bbl-and-wbbl-draft-1448913",
    "9": "https://www.espncricinfo.com/story/faq-wbbl-and-bbl-drafts-all-you-need-to-know-picks-order-and-prices-1448902",
    "10": "https://www.daily-sun.com/post/774506",
    "11": "https://www.cricket.com.au/news/3999654/every-squad-updated-lists-big-bash-2024-25-bbl14-ins-and-outs-strikers-heat-hurricanes-renegades-stars-scorchers-sixers-thunder?",
    "12": "https://www.espncricinfo.com/story/all-the-bbl14-and-wbbl10-squads-for-2024-25-season-1440939",
    "17": "https://www.austadiums.com/sport/event/30395",
    "18": "https://www.austadiums.com/sport/event/30396",
    "19": "https://www.austadiums.com/sport/event/30397",
    "20": "https://www.probatsman.com/cricket-news/bbl-2024-25-sam-konstas-rewrites-history-with-the-fastest-fifty-on-debut-for-sydney-thunder",
    "21": "https://www.austadiums.com/sport/event/30398",
    "22": "https://www.austadiums.com/sport/event/30399",
    "23": "https://www.probatsman.com/cricket-news/hobart-hurricanes-bowled-out-for-their-lowest-ever-total-in-bbl-history",
    "24": "https://www.austadiums.com/sport/event/30400",
    "25": "https://www.austadiums.com/sport/event/30401",
    "26": "https://www.probatsman.com/cricket-news/hobart-hurricanes-sensation-mitchell-owen-blasts-perth-scorchers-with-a-jaw-dropping-century-in-bbl-2024-25",
    "27": "https://www.espncricinfo.com/story/bbl-mitch-owen-s-maiden-t20-century-topples-powerhouse-perth-scorchers-1466079",
    "28": "https://www.austadiums.com/sport/event/30402",
    "29": "https://www.austadiums.com/sport/event/30403",
    "30": "https://www.austadiums.com/sport/event/30404",
    "31": "https://www.austadiums.com/sport/event/30405",
    "32": "https://www.austadiums.com/sport/event/30406",
    "33": "https://www.austadiums.com/sport/event/30407",
    "34": "https://www.austadiums.com/sport/event/30408",
    "35": "https://www.austadiums.com/sport/event/30409",
    "36": "https://www.austadiums.com/sport/event/30410",
    "37": "https://www.austadiums.com/sport/event/30411",
    "38": "https://www.austadiums.com/sport/event/30412",
    "39": "https://www.austadiums.com/sport/event/30413",
    "40": "https://www.austadiums.com/sport/event/30414",
    "41": "https://www.austadiums.com/sport/event/30415",
    "42": "https://www.austadiums.com/sport/event/30416",
    "43": "https://www.austadiums.com/sport/event/30417",
    "44": "https://www.austadiums.com/sport/event/30418",
    "45": "https://www.austadiums.com/sport/event/30419",
    "46": "https://www.austadiums.com/sport/event/30420",
    "47": "https://www.austadiums.com/sport/event/30421",
    "48": "https://www.austadiums.com/sport/event/30422",
    "49": "https://www.austadiums.com/sport/event/30423",
    "50": "https://www.austadiums.com/sport/event/30424",
    "51": "https://www.austadiums.com/sport/event/30425",
    "52": "https://www.austadiums.com/sport/event/30426",
    "53": "https://www.austadiums.com/sport/event/30427",
    "54": "https://www.austadiums.com/sport/event/30428",
    "55": "https://www.austadiums.com/sport/event/30429",
    "56": "https://www.austadiums.com/sport/event/30430",
    "57": "https://www.austadiums.com/sport/event/30431",
    "58": "https://www.austadiums.com/sport/event/30432",
    "59": "https://www.austadiums.com/sport/event/30433",
    "60": "https://www.austadiums.com/sport/event/30434",
    "61": "https://www.austadiums.com/sport/event/30435",
    "62": "https://www.austadiums.com/sport/event/30436",
    "63": "https://www.espncricinfo.com/series/big-bash-league-2024-25-1443056/sydney-thunder-vs-melbourne-stars-knockout-1443098/match-report",
    "64": "https://www.austadiums.com/sport/event/30437",
    "65": "https://www.austadiums.com/sport/event/30438",
    "67": "https://www.austadiums.com/sport/event/30431"
  },
  "flair_entities": [
    "bangladesh premier league",
    "bbl 14 team of the tournament",
    "sydney thunder",
    "cricket australia",
    "tournament  the big bash",
    "super smash",
    "melbourne stars",
    "big bash league",
    "australia",
    "international league t20",
    "sa20",
    "bbl",
    "brisbane heat"
  ]
}